epystemology/__init__.py
epystemology-0.0.1.dist-info/METADATA
epystemology-0.0.1.dist-info/WHEEL
epystemology-0.0.1.dist-info/licenses/LICENSE.txt
epystemology-0.0.1.dist-info/RECORD
